supermorecado/__init__.py
supermorecado/burntiles.py
supermorecado/densitytiles.py
supermorecado/edge_finder.py
supermorecado/py.typed
supermorecado/super_utils.py
supermorecado/uniontiles.py
supermorecado/scripts/__init__.py
supermorecado/scripts/cli.py
supermorecado-0.1.1.dist-info/entry_points.txt
supermorecado-0.1.1.dist-info/LICENSE
supermorecado-0.1.1.dist-info/WHEEL
supermorecado-0.1.1.dist-info/METADATA
supermorecado-0.1.1.dist-info/RECORD
