Metadata-Version: 2.1
Name: supermorecado
Version: 0.1.1
Summary: Extend the functionality of morecantile with additional commands.
Keywords: GIS,TMS,TileMatrixSet,Map Tile
Author-email: Vincent Sarago <vincent@developmentseed.com>
Requires-Python: >=3.8
Classifier: Intended Audience :: Information Technology
Classifier: Intended Audience :: Science/Research
Classifier: License :: OSI Approved :: BSD License
Classifier: Programming Language :: Python :: 3.8
Classifier: Programming Language :: Python :: 3.9
Classifier: Programming Language :: Python :: 3.10
Classifier: Programming Language :: Python :: 3.11
Classifier: Topic :: Scientific/Engineering :: GIS
Requires-Dist: morecantile
Requires-Dist: rasterio
Requires-Dist: pre-commit ; extra == "dev"
Requires-Dist: mkdocs ; extra == "docs"
Requires-Dist: mkdocs-material ; extra == "docs"
Requires-Dist: pygments ; extra == "docs"
Requires-Dist: pytest ; extra == "test"
Requires-Dist: pytest-cov ; extra == "test"
Project-URL: Documentation, https://developmentseed.org/supermorecado/
Project-URL: Source, https://github.com/developmentseed/supermorecado
Provides-Extra: dev
Provides-Extra: docs
Provides-Extra: test
